<?xml version="1.0" encoding="UTF-8"?>
<LanguageData>

  <!-- EN: 12 gauge shell (Bean) -->
  <Ammo_12Gauge_Beanbag.label>12 号子弹（豆袋弹）</Ammo_12Gauge_Beanbag.label>
  <!-- EN: Extremely common shotgun caliber used in almost every application, from hunting over riot control to military firearms. -->
  <Ammo_12Gauge_Beanbag.description>极为常见的霰弹枪口径，从狩猎到防暴，再到军用枪械，几乎随处可见。</Ammo_12Gauge_Beanbag.description>
  <!-- EN: 极为常见的霰弹枪口径，从狩猎到防暴，再到军用枪械，几乎随处可见。\n(Core SK) -->
  <Ammo_12Gauge_Beanbag.oldDescription>极为常见的霰弹枪口径，从狩猎到防暴，再到军用枪械，几乎随处可见。</Ammo_12Gauge_Beanbag.oldDescription>

  <!-- EN: 12 gauge shell (Bird) -->
  <Ammo_12Gauge_Bird.label>12 号子弹（鸟弹）</Ammo_12Gauge_Bird.label>
  <!-- EN: Extremely common shotgun caliber used in almost every application, from hunting over riot control to military firearms. -->
  <Ammo_12Gauge_Bird.description>极为常见的霰弹枪口径，从狩猎到防暴，再到军用枪械，几乎随处可见。</Ammo_12Gauge_Bird.description>
  <!-- EN: 极为常见的霰弹枪口径，从狩猎到防暴，再到军用枪械，几乎随处可见。\n(Core SK) -->
  <Ammo_12Gauge_Bird.oldDescription>极为常见的霰弹枪口径，从狩猎到防暴，再到军用枪械，几乎随处可见。</Ammo_12Gauge_Bird.oldDescription>

  <!-- EN: 12 gauge shell (Buck) -->
  <Ammo_12Gauge_Buck.label>12 号子弹（鹿弹）</Ammo_12Gauge_Buck.label>
  <!-- EN: Extremely common shotgun caliber used in almost every application, from hunting over riot control to military firearms. -->
  <Ammo_12Gauge_Buck.description>极为常见的霰弹枪口径，从狩猎到防暴，再到军用枪械，几乎随处可见。</Ammo_12Gauge_Buck.description>
  <!-- EN: 极为常见的霰弹枪口径，从狩猎到防暴，再到军用枪械，几乎随处可见。\n(Core SK) -->
  <Ammo_12Gauge_Buck.oldDescription>极为常见的霰弹枪口径，从狩猎到防暴，再到军用枪械，几乎随处可见。</Ammo_12Gauge_Buck.oldDescription>

  <!-- EN: 12 gauge shell (EMP) -->
  <Ammo_12Gauge_ElectroSlug.label>12 号子弹（EMP）</Ammo_12Gauge_ElectroSlug.label>
  <!-- EN: Extremely common shotgun caliber used in almost every application, from hunting over riot control to military firearms. -->
  <Ammo_12Gauge_ElectroSlug.description>极为常见的霰弹枪口径，从狩猎到防暴，再到军用枪械，几乎随处可见。</Ammo_12Gauge_ElectroSlug.description>
  <!-- EN: 极为常见的霰弹枪口径，从狩猎到防暴，再到军用枪械，几乎随处可见。\n(Core SK) -->
  <Ammo_12Gauge_ElectroSlug.oldDescription>极为常见的霰弹枪口径，从狩猎到防暴，再到军用枪械，几乎随处可见。</Ammo_12Gauge_ElectroSlug.oldDescription>

  <!-- EN: 12 gauge shell (Slug) -->
  <Ammo_12Gauge_Slug.label>12 号子弹（独头弹）</Ammo_12Gauge_Slug.label>
  <!-- EN: Extremely common shotgun caliber used in almost every application, from hunting over riot control to military firearms. -->
  <Ammo_12Gauge_Slug.description>极为常见的霰弹枪口径，从狩猎到防暴，再到军用枪械，几乎随处可见。</Ammo_12Gauge_Slug.description>
  <!-- EN: 极为常见的霰弹枪口径，从狩猎到防暴，再到军用枪械，几乎随处可见。\n(Core SK) -->
  <Ammo_12Gauge_Slug.oldDescription>极为常见的霰弹枪口径，从狩猎到防暴，再到军用枪械，几乎随处可见。</Ammo_12Gauge_Slug.oldDescription>

  <!-- EN: beanbag -->
  <Bullet_12Gauge_Beanbag.label>豆袋弹</Bullet_12Gauge_Beanbag.label>

  <!-- EN: birdshot pellet -->
  <Bullet_12Gauge_Bird.label>鸟弹</Bullet_12Gauge_Bird.label>

  <!-- EN: buckshot pellet -->
  <Bullet_12Gauge_Buck.label>鹿弹</Bullet_12Gauge_Buck.label>

  <!-- EN: EMP slug -->
  <Bullet_12Gauge_ElectroSlug.label>EMP弹</Bullet_12Gauge_ElectroSlug.label>

  <!-- EN: shotgun slug -->
  <Bullet_12Gauge_Slug.label>独头弹</Bullet_12Gauge_Slug.label>

</LanguageData>