<?xml version="1.0" encoding="utf-8"?>
<LanguageData>

  <Efficient.degreeDatas.0.label>efficient worker</Efficient.degreeDatas.0.label>
  <Efficient.degreeDatas.0.description>NAME is a highly efficient worker, resulting in increased productivity.</Efficient.degreeDatas.0.description>


  <!-- error! -->

  <Slacker.degreeDatas.0.label>slacker</Slacker.degreeDatas.0.label>
  <Slacker.degreeDatas.0.description>NAME is a slacker and spends as little time as possible working.</Slacker.degreeDatas.0.description>

  <Focused.degreeDatas.0.label>focused</Focused.degreeDatas.0.label>
  <Focused.degreeDatas.0.description>NAME is focused and gets things done slightly faster.</Focused.degreeDatas.0.description>

  <Forgetful.degreeDatas.0.label>forgetful</Forgetful.degreeDatas.0.label>
  <Forgetful.degreeDatas.0.description>NAME is forgetful and gets things done slightly slower.</Forgetful.degreeDatas.0.description>

  <LazyEye.degreeDatas.0.label>lazyeye'd</LazyEye.degreeDatas.0.label>
  <LazyEye.degreeDatas.0.description>NAME has a rather unfortunate disability for being on a RimWorld. HECAP has a lazy-eye, making hitting anything much harder</LazyEye.degreeDatas.0.description>

  <Marksman.degreeDatas.0.label>marksman</Marksman.degreeDatas.0.label>
  <Marksman.degreeDatas.0.description>NAME has displayed a natural affinity for ranged weapons and abhors close quarters combat. </Marksman.degreeDatas.0.description>

  <Fat.degreeDatas.0.label>fat</Fat.degreeDatas.0.label>
  <Fat.degreeDatas.0.description>NAME hates exercise, and despite the fact that HE eats as much as a normal person, HIS sedentary lifestyle has made HIM exceptionally fat.</Fat.degreeDatas.0.description>

  <Fit.degreeDatas.0.label>fit</Fit.degreeDatas.0.label>
  <Fit.degreeDatas.0.description>NAME loves exercise, and HIS time spent conditioning HIS body has paid off.</Fit.degreeDatas.0.description>


  <!-- error! RNRV Remove in next rimworld version -->

  <Agoraphobia.degreeDatas.0.label>agoraphobic</Agoraphobia.degreeDatas.0.label>
  <Agoraphobia.degreeDatas.0.description>NAME has a fear of open spaces, while HE can manage relatively fine in them, HE is much more comfortable indoors.</Agoraphobia.degreeDatas.0.description>


</LanguageData>