<?xml version="1.0" encoding="utf-8"?>
<LanguageData>

  <!-- SVD -->

  <Build_HMC_Gun_SVD.label>制造 SVD狙击步枪</Build_HMC_Gun_SVD.label>
  <Build_HMC_Gun_SVD.description>制造一把威力可观，射程超长并且拥有较高精度的狙击步枪。\n弹种：7.62x54mmR子弹</Build_HMC_Gun_SVD.description>
  <Build_HMC_Gun_SVD.jobString>正在制造 SVD狙击步枪。</Build_HMC_Gun_SVD.jobString>


  <!-- VSS Vintorez -->

  <BuildVintorezRifle.label>制造 VSS“螺纹剪裁机”狙击步枪</BuildVintorezRifle.label>
  <BuildVintorezRifle.description>制造VSS“螺纹剪裁机”狙击步枪，一种应用于特种部队的狙击步枪。在较长的距离上拥有极好的精度，发射速率较高，并且其载弹量较高。\n弹种：9x39mm子弹</BuildVintorezRifle.description>
  <BuildVintorezRifle.jobString>正在制造 VSS“螺纹剪裁机”狙击步枪。</BuildVintorezRifle.jobString>


</LanguageData>