<?xml version="1.0" encoding="utf-8"?>
<LanguageData>

  <EmptyCrate_cider.label>拆开 苹果酒箱子</EmptyCrate_cider.label>
  <EmptyCrate_cider.description>把所有包装好的瓶装酒从储藏箱里拿出来。</EmptyCrate_cider.description>
  <EmptyCrate_cider.jobString>打开箱子。</EmptyCrate_cider.jobString>

  <EmptyCrate_rum.label>拆开 朗姆酒箱子</EmptyCrate_rum.label>
  <EmptyCrate_rum.description>把所有包装好的瓶装酒从储藏箱里拿出来。</EmptyCrate_rum.description>
  <EmptyCrate_rum.jobString>打开箱子。</EmptyCrate_rum.jobString>

  <EmptyCrate_Wine.label>拆开 葡萄酒箱子</EmptyCrate_Wine.label>
  <EmptyCrate_Wine.description>把所有包装好的瓶装酒从储藏箱里拿出来。</EmptyCrate_Wine.description>
  <EmptyCrate_Wine.jobString>打开箱子。</EmptyCrate_Wine.jobString>

  <EmptyCrate_strawberrywine.label>拆开 浆果酒箱子</EmptyCrate_strawberrywine.label>
  <EmptyCrate_strawberrywine.description>把所有包装好的瓶装酒从储藏箱里拿出来。</EmptyCrate_strawberrywine.description>
  <EmptyCrate_strawberrywine.jobString>打开箱子。</EmptyCrate_strawberrywine.jobString>

  <EmptyCrate_saki.label>拆开 清酒箱子</EmptyCrate_saki.label>
  <EmptyCrate_saki.description>把所有包装好的瓶装酒从储藏箱里拿出来。</EmptyCrate_saki.description>
  <EmptyCrate_saki.jobString>打开箱子。</EmptyCrate_saki.jobString>

  <EmptyCrate_vodka.label>拆开 伏特加箱子</EmptyCrate_vodka.label>
  <EmptyCrate_vodka.description>把所有包装好的瓶装酒从储藏箱里拿出来。</EmptyCrate_vodka.description>
  <EmptyCrate_vodka.jobString>打开箱子。</EmptyCrate_vodka.jobString>

  <EmptyCrate_tequila.label>拆开 龙舌兰酒箱子</EmptyCrate_tequila.label>
  <EmptyCrate_tequila.description>把所有包装好的瓶装酒从储藏箱里拿出来。</EmptyCrate_tequila.description>
  <EmptyCrate_tequila.jobString>打开箱子。</EmptyCrate_tequila.jobString>

  <EmptyCrate_Whiskey.label>拆开 威士忌箱子</EmptyCrate_Whiskey.label>
  <EmptyCrate_Whiskey.description>把所有包装好的瓶装酒从储藏箱里拿出来。</EmptyCrate_Whiskey.description>
  <EmptyCrate_Whiskey.jobString>打开箱子。</EmptyCrate_Whiskey.jobString>

  <EmptyCrate_Moonshine.label>拆开 月光佳酿箱子</EmptyCrate_Moonshine.label>
  <EmptyCrate_Moonshine.description>把所有包装好的瓶装酒从储藏箱里拿出来。</EmptyCrate_Moonshine.description>
  <EmptyCrate_Moonshine.jobString>打开箱子。</EmptyCrate_Moonshine.jobString>

  <EmptyCrate_Gin.label>拆开 杜松子酒箱子</EmptyCrate_Gin.label>
  <EmptyCrate_Gin.description>把所有包装好的瓶装酒从储藏箱里拿出来。</EmptyCrate_Gin.description>
  <EmptyCrate_Gin.jobString>打开箱子。</EmptyCrate_Gin.jobString>

  <EmptyCrate_Brandy.label>拆开 白兰地箱子</EmptyCrate_Brandy.label>
  <EmptyCrate_Brandy.description>把所有包装好的瓶装酒从储藏箱里拿出来。</EmptyCrate_Brandy.description>
  <EmptyCrate_Brandy.jobString>打开箱子。</EmptyCrate_Brandy.jobString>

  <EmptyCrate_Cognac.label>拆开 干邑白兰地箱子</EmptyCrate_Cognac.label>
  <EmptyCrate_Cognac.description>把所有包装好的瓶装酒从储藏箱里拿出来。</EmptyCrate_Cognac.description>
  <EmptyCrate_Cognac.jobString>打开箱子。</EmptyCrate_Cognac.jobString>

  <EmptyCrate_Kahlua.label>拆开 咖啡酒箱子</EmptyCrate_Kahlua.label>
  <EmptyCrate_Kahlua.description>把所有包装好的瓶装酒从储藏箱里拿出来。</EmptyCrate_Kahlua.description>
  <EmptyCrate_Kahlua.jobString>打开箱子。</EmptyCrate_Kahlua.jobString>

  <EmptyCrate_Arak.label>拆开 亚力酒箱子</EmptyCrate_Arak.label>
  <EmptyCrate_Arak.description>把所有包装好的瓶装酒从储藏箱里拿出来。</EmptyCrate_Arak.description>
  <EmptyCrate_Arak.jobString>打开箱子。</EmptyCrate_Arak.jobString>

  <EmptyCrate_Applejack.label>拆开 苹果白兰地箱子</EmptyCrate_Applejack.label>
  <EmptyCrate_Applejack.description>把所有包装好的瓶装酒从储藏箱里拿出来。</EmptyCrate_Applejack.description>
  <EmptyCrate_Applejack.jobString>打开箱子。</EmptyCrate_Applejack.jobString>

  <EmptyCrate_Patreonbrew.label>拆开 众筹佳酿箱子</EmptyCrate_Patreonbrew.label>
  <EmptyCrate_Patreonbrew.description>把所有包装好的瓶装酒从储藏箱里拿出来。</EmptyCrate_Patreonbrew.description>
  <EmptyCrate_Patreonbrew.jobString>打开箱子。</EmptyCrate_Patreonbrew.jobString>


</LanguageData>